Workbook

Sheet Dashboard
B2: CHRISTMAN BIG — BID-TO-HIT DASHBOARD ⬛
B4: Structural Concrete Estimation History | Auto-calculated from Estimating tab
B6: Total Bids (excl. Open) | D6: Awarded | F6: Closed (Lost) | H6: Bid-to-Hit Ratio | J6: Avg Bid Amount | L6: Avg Contract (Awarded)
B7: =COUNTIF(Estimating!A2:A200,"Awarded")+COUNTIF(Estimating!A2:A200,"Closed") -> 95 | D7: =COUNTIF(Estimating!A2:A200,"Awarded") -> 19 | F7: =COUNTIF(Estimating!A2:A200,"Closed") -> 76 | H7: =IFERROR(COUNTIF(Estimating!A2:A200,"Awarded")/(COUNTIF(Estimating!A2:A200,"Awarded")+COUNTIF(Estimating!A2:A200,"Closed")),0) -> 0.2 | J7: =IFERROR(AVERAGEIF(Estimating!A2:A200,"<>Open",Estimating!J2:J200),0) -> 2053584.4 | L7: =IFERROR(AVERAGEIF(Estimating!A2:A200,"Awarded",Estimating!N2:N200),0) -> 777297.32
B9: ⬛ HIT RATE BY MARKET SECTOR | H9: ⬛ HIT RATE BY ESTIMATOR
B10: Market Sector | C10: Bids | D10: Awarded | E10: Hit Rate | H10: Estimator | I10: Bids | J10: Awarded | K10: Hit Rate
B11: Church | C11: =COUNTIFS(Estimating!C$2:C$200,B11,Estimating!A$2:A$200,"<>Open") -> 1 | D11: =COUNTIFS(Estimating!C$2:C$200,B11,Estimating!A$2:A$200,"Awarded") -> 0 | E11: =IFERROR(D11/C11,"-") -> 0 | H11: Christian Oglesby | I11: =COUNTIFS(Estimating!M$2:M$200,H11,Estimating!A$2:A$200,"<>Open") -> 2 | J11: =COUNTIFS(Estimating!M$2:M$200,H11,Estimating!A$2:A$200,"Awarded") -> 0 | K11: =IFERROR(J11/I11,"-") -> 0
B12: Elem/High School | C12: =COUNTIFS(Estimating!C$2:C$200,B12,Estimating!A$2:A$200,"<>Open") -> 4 | D12: =COUNTIFS(Estimating!C$2:C$200,B12,Estimating!A$2:A$200,"Awarded") -> 1 | E12: =IFERROR(D12/C12,"-") -> 0.25 | H12: Dave Deller | I12: =COUNTIFS(Estimating!M$2:M$200,H12,Estimating!A$2:A$200,"<>Open") -> 26 | J12: =COUNTIFS(Estimating!M$2:M$200,H12,Estimating!A$2:A$200,"Awarded") -> 5 | K12: =IFERROR(J12/I12,"-") -> 0.19230769
B13: Government | C13: =COUNTIFS(Estimating!C$2:C$200,B13,Estimating!A$2:A$200,"<>Open") -> 28 | D13: =COUNTIFS(Estimating!C$2:C$200,B13,Estimating!A$2:A$200,"Awarded") -> 5 | E13: =IFERROR(D13/C13,"-") -> 0.17857143 | H13: Ethan Conlan | I13: =COUNTIFS(Estimating!M$2:M$200,H13,Estimating!A$2:A$200,"<>Open") -> 9 | J13: =COUNTIFS(Estimating!M$2:M$200,H13,Estimating!A$2:A$200,"Awarded") -> 0 | K13: =IFERROR(J13/I13,"-") -> 0
B14: Health Care | C14: =COUNTIFS(Estimating!C$2:C$200,B14,Estimating!A$2:A$200,"<>Open") -> 6 | D14: =COUNTIFS(Estimating!C$2:C$200,B14,Estimating!A$2:A$200,"Awarded") -> 2 | E14: =IFERROR(D14/C14,"-") -> 0.33333333 | H14: Farzan Rafieyan-Esfahani | I14: =COUNTIFS(Estimating!M$2:M$200,H14,Estimating!A$2:A$200,"<>Open") -> 23 | J14: =COUNTIFS(Estimating!M$2:M$200,H14,Estimating!A$2:A$200,"Awarded") -> 8 | K14: =IFERROR(J14/I14,"-") -> 0.34782609
B15: Higher Ed | C15: =COUNTIFS(Estimating!C$2:C$200,B15,Estimating!A$2:A$200,"<>Open") -> 1 | D15: =COUNTIFS(Estimating!C$2:C$200,B15,Estimating!A$2:A$200,"Awarded") -> 0 | E15: =IFERROR(D15/C15,"-") -> 0 | H15: Frank Duff | I15: =COUNTIFS(Estimating!M$2:M$200,H15,Estimating!A$2:A$200,"<>Open") -> 3 | J15: =COUNTIFS(Estimating!M$2:M$200,H15,Estimating!A$2:A$200,"Awarded") -> 0 | K15: =IFERROR(J15/I15,"-") -> 0
B16: Historic Preservation | C16: =COUNTIFS(Estimating!C$2:C$200,B16,Estimating!A$2:A$200,"<>Open") -> 1 | D16: =COUNTIFS(Estimating!C$2:C$200,B16,Estimating!A$2:A$200,"Awarded") -> 0 | E16: =IFERROR(D16/C16,"-") -> 0 | H16: Greg Klem | I16: =COUNTIFS(Estimating!M$2:M$200,H16,Estimating!A$2:A$200,"<>Open") -> 28 | J16: =COUNTIFS(Estimating!M$2:M$200,H16,Estimating!A$2:A$200,"Awarded") -> 5 | K16: =IFERROR(J16/I16,"-") -> 0.17857143
B17: Industrial/Power | C17: =COUNTIFS(Estimating!C$2:C$200,B17,Estimating!A$2:A$200,"<>Open") -> 29 | D17: =COUNTIFS(Estimating!C$2:C$200,B17,Estimating!A$2:A$200,"Awarded") -> 9 | E17: =IFERROR(D17/C17,"-") -> 0.31034483 | H17: Joseph Leone | I17: =COUNTIFS(Estimating!M$2:M$200,H17,Estimating!A$2:A$200,"<>Open") -> 2 | J17: =COUNTIFS(Estimating!M$2:M$200,H17,Estimating!A$2:A$200,"Awarded") -> 1 | K17: =IFERROR(J17/I17,"-") -> 0.5
B18: Office | C18: =COUNTIFS(Estimating!C$2:C$200,B18,Estimating!A$2:A$200,"<>Open") -> 2 | D18: =COUNTIFS(Estimating!C$2:C$200,B18,Estimating!A$2:A$200,"Awarded") -> 0 | E18: =IFERROR(D18/C18,"-") -> 0 | H18: Ron Cody | I18: =COUNTIFS(Estimating!M$2:M$200,H18,Estimating!A$2:A$200,"<>Open") -> 1 | J18: =COUNTIFS(Estimating!M$2:M$200,H18,Estimating!A$2:A$200,"Awarded") -> 0 | K18: =IFERROR(J18/I18,"-") -> 0
B19: Other | C19: =COUNTIFS(Estimating!C$2:C$200,B19,Estimating!A$2:A$200,"<>Open") -> 10 | D19: =COUNTIFS(Estimating!C$2:C$200,B19,Estimating!A$2:A$200,"Awarded") -> 2 | E19: =IFERROR(D19/C19,"-") -> 0.2 | H19: Sam Peterson | I19: =COUNTIFS(Estimating!M$2:M$200,H19,Estimating!A$2:A$200,"<>Open") -> 1 | J19: =COUNTIFS(Estimating!M$2:M$200,H19,Estimating!A$2:A$200,"Awarded") -> 0 | K19: =IFERROR(J19/I19,"-") -> 0
B20: Parking Deck | C20: =COUNTIFS(Estimating!C$2:C$200,B20,Estimating!A$2:A$200,"<>Open") -> 1 | D20: =COUNTIFS(Estimating!C$2:C$200,B20,Estimating!A$2:A$200,"Awarded") -> 0 | E20: =IFERROR(D20/C20,"-") -> 0
B21: Residential/ Housing | C21: =COUNTIFS(Estimating!C$2:C$200,B21,Estimating!A$2:A$200,"<>Open") -> 7 | D21: =COUNTIFS(Estimating!C$2:C$200,B21,Estimating!A$2:A$200,"Awarded") -> 0 | E21: =IFERROR(D21/C21,"-") -> 0
B22: Retail | C22: =COUNTIFS(Estimating!C$2:C$200,B22,Estimating!A$2:A$200,"<>Open") -> 3 | D22: =COUNTIFS(Estimating!C$2:C$200,B22,Estimating!A$2:A$200,"Awarded") -> 0 | E22: =IFERROR(D22/C22,"-") -> 0
B23: Sports / Event Venues | C23: =COUNTIFS(Estimating!C$2:C$200,B23,Estimating!A$2:A$200,"<>Open") -> 2 | D23: =COUNTIFS(Estimating!C$2:C$200,B23,Estimating!A$2:A$200,"Awarded") -> 0 | E23: =IFERROR(D23/C23,"-") -> 0
B26: ⬛ HIT RATE BY REGION | H26: ⬛ BID VOLUME BY MONTH
B27: Region | C27: Bids | D27: Awarded | E27: Hit Rate | H27: Month | I27: Bids | J27: Awarded | K27: Hit Rate
B28: CCI Central MI | C28: =COUNTIFS(Estimating!B$2:B$200,B28,Estimating!A$2:A$200,"<>Open") -> 51 | D28: =COUNTIFS(Estimating!B$2:B$200,B28,Estimating!A$2:A$200,"Awarded") -> 12 | E28: =IFERROR(D28/C28,"-") -> 0.23529412 | H28: Jan | I28: =COUNTIFS(Estimating!D$2:D$200,1,Estimating!A$2:A$200,"<>Open") -> 7 | J28: =COUNTIFS(Estimating!D$2:D$200,1,Estimating!A$2:A$200,"Awarded") -> 1 | K28: =IFERROR(J28/I28,"-") -> 0.14285714
B29: CCI Southeast MI | C29: =COUNTIFS(Estimating!B$2:B$200,B29,Estimating!A$2:A$200,"<>Open") -> 38 | D29: =COUNTIFS(Estimating!B$2:B$200,B29,Estimating!A$2:A$200,"Awarded") -> 7 | E29: =IFERROR(D29/C29,"-") -> 0.18421053 | H29: Feb | I29: =COUNTIFS(Estimating!D$2:D$200,2,Estimating!A$2:A$200,"<>Open") -> 12 | J29: =COUNTIFS(Estimating!D$2:D$200,2,Estimating!A$2:A$200,"Awarded") -> 6 | K29: =IFERROR(J29/I29,"-") -> 0.5
B30: CCI West Michigan | C30: =COUNTIFS(Estimating!B$2:B$200,B30,Estimating!A$2:A$200,"<>Open") -> 3 | D30: =COUNTIFS(Estimating!B$2:B$200,B30,Estimating!A$2:A$200,"Awarded") -> 0 | E30: =IFERROR(D30/C30,"-") -> 0 | H30: Mar | I30: =COUNTIFS(Estimating!D$2:D$200,3,Estimating!A$2:A$200,"<>Open") -> 4 | J30: =COUNTIFS(Estimating!D$2:D$200,3,Estimating!A$2:A$200,"Awarded") -> 0 | K30: =IFERROR(J30/I30,"-") -> 0
B31: Out of Region | C31: =COUNTIFS(Estimating!B$2:B$200,B31,Estimating!A$2:A$200,"<>Open") -> 3 | D31: =COUNTIFS(Estimating!B$2:B$200,B31,Estimating!A$2:A$200,"Awarded") -> 0 | E31: =IFERROR(D31/C31,"-") -> 0 | H31: Apr | I31: =COUNTIFS(Estimating!D$2:D$200,4,Estimating!A$2:A$200,"<>Open") -> 14 | J31: =COUNTIFS(Estimating!D$2:D$200,4,Estimating!A$2:A$200,"Awarded") -> 2 | K31: =IFERROR(J31/I31,"-") -> 0.14285714
H32: May | I32: =COUNTIFS(Estimating!D$2:D$200,5,Estimating!A$2:A$200,"<>Open") -> 11 | J32: =COUNTIFS(Estimating!D$2:D$200,5,Estimating!A$2:A$200,"Awarded") -> 2 | K32: =IFERROR(J32/I32,"-") -> 0.18181818
H33: Jun | I33: =COUNTIFS(Estimating!D$2:D$200,6,Estimating!A$2:A$200,"<>Open") -> 6 | J33: =COUNTIFS(Estimating!D$2:D$200,6,Estimating!A$2:A$200,"Awarded") -> 2 | K33: =IFERROR(J33/I33,"-") -> 0.33333333
H34: Jul | I34: =COUNTIFS(Estimating!D$2:D$200,7,Estimating!A$2:A$200,"<>Open") -> 9 | J34: =COUNTIFS(Estimating!D$2:D$200,7,Estimating!A$2:A$200,"Awarded") -> 0 | K34: =IFERROR(J34/I34,"-") -> 0
H35: Aug | I35: =COUNTIFS(Estimating!D$2:D$200,8,Estimating!A$2:A$200,"<>Open") -> 5 | J35: =COUNTIFS(Estimating!D$2:D$200,8,Estimating!A$2:A$200,"Awarded") -> 1 | K35: =IFERROR(J35/I35,"-") -> 0.2
H36: Sep | I36: =COUNTIFS(Estimating!D$2:D$200,9,Estimating!A$2:A$200,"<>Open") -> 6 | J36: =COUNTIFS(Estimating!D$2:D$200,9,Estimating!A$2:A$200,"Awarded") -> 1 | K36: =IFERROR(J36/I36,"-") -> 0.16666667
H37: Oct | I37: =COUNTIFS(Estimating!D$2:D$200,10,Estimating!A$2:A$200,"<>Open") -> 5 | J37: =COUNTIFS(Estimating!D$2:D$200,10,Estimating!A$2:A$200,"Awarded") -> 0 | K37: =IFERROR(J37/I37,"-") -> 0
H38: Nov | I38: =COUNTIFS(Estimating!D$2:D$200,11,Estimating!A$2:A$200,"<>Open") -> 8 | J38: =COUNTIFS(Estimating!D$2:D$200,11,Estimating!A$2:A$200,"Awarded") -> 2 | K38: =IFERROR(J38/I38,"-") -> 0.25
H39: Dec | I39: =COUNTIFS(Estimating!D$2:D$200,12,Estimating!A$2:A$200,"<>Open") -> 8 | J39: =COUNTIFS(Estimating!D$2:D$200,12,Estimating!A$2:A$200,"Awarded") -> 2 | K39: =IFERROR(J39/I39,"-") -> 0.25
B42: 📌 HOW TO IMPROVE BID-TO-HIT: Fill in the gold-highlighted columns on the Estimating tab — Delivery Method, Opportunity Source, Go/No-Go Score, Loss Reason, Competitor Who Won, and # of Bidders. Once populated, you can add COUNTIFS breakdowns here (or in a pivot table) to see which delivery methods, opportunity sources, and estimators drive the best win rates. The Bid Delta % column auto-calculates on awarded jobs.

Sheet Estimating
A1: Status | B1: Region | C1: Market Sector | D1: Month | E1: Job # | F1: Estimate # | G1: Name | H1: Bid Date | I1: Sales Date | J1: Bid Amount | K1: Location | L1: Trade | M1: Estimator | N1: Contract Amount | O1: Contract Fee | P1: Contract Hours | Q1: Comments | R1: Conc Vol (CY) | S1: Building SF | T1: Production MH | U1: Installation MH | V1: GC MH | W1: Total MH | X1: Fee | Y1: Duration (PM) Weeks | Z1: Total GC Labor | AA1: Staff Labor Hours | AB1: Total GC's | AC1: GC % | AD1: Customer | AE1: Final Hours | AF1: WIP Est Cost | AG1: WIP Est Fee | AH1: WIP Est Contract | AI1: WIP Fee % | AJ1: Contract Status | AK1: Job Start Date | AL1: Job End Date | AM1: Weeks | AN1: Equipment Value | AO1: Delivery Method | AP1: # of Bidders | AQ1: Opportunity Source | AR1: Go/No-Go Score (1=Low 3=High) | AS1: Loss Reason | AT1: Competitor Who Won | AU1: Our Rank (if lost) | AV1: Bid Delta % (Contract vs Bid)
A2: Awarded | B2: CCI Southeast MI | C2: Health Care | D2: 6 | E2: 251121 | F2: 24-0378 | G2: McKenzie Health System - WC 10 | H2: 6/11/2024 | I2: 9/26/2025 | J2: 1597000 | K2: Sandusky, MI | L2: CON | M2: Greg Klem | N2: 1800550 | O2: 140911 | P2: 9682 | R2: 1525 | S2: 71670 | T2: 6362 | V2: 2440 | W2: 8802 | X2: 144763 | Y2: 14 | Z2: 183489 | AA2: 1680 | AB2: 320044 | AC2: 20% | AD2: The Christman Company - 0 | AE2: 4834.75 | AF2: 1658050 | AG2: 152500 | AH2: 1810550 | AI2: 8.4% | AJ2: Open | AK2: 45139 | AM2: 0 | AN2: 156372 | AO2: Hard Bid | AV2: =IF(A2="Awarded",IFERROR((N2-J2)/J2,"-"),"-") -> 0.12745773
A3: Awarded | B3: CCI Southeast MI | C3: Industrial/Power | D3: 6 | E3: 251039 | F3: 24-0402 | G3: GLWA Final Screened Effluent Pump Station CONCRETE | H3: 6/25/2024 | I3: 4/28/2025 | J3: 3147964 | K3: Detroit, MI | L3: CON | M3: Joseph Leone | N3: 3155940 | O3: 331190 | P3: 15518 | R3: 4413 | S3: 73800 | T3: 12491 | V3: 3027 | W3: 15518 | X3: 331934 | Y3: 32 | Z3: 352947 | AA3: 3072 | AB3: 556823 | AC3: 18% | AD3: FH Paschen - 0 | AE3: 424.5 | AF3: 3131076 | AG3: 195070 | AH3: 3326146 | AI3: 5.9% | AJ3: Open | AK3: 45689 | AM3: 0 | AV3: =IF(A3="Awarded",IFERROR((N3-J3)/J3,"-"),"-") -> 0.0025337011
A4: Awarded | B4: CCI Central MI | C4: Industrial/Power | D4: 11 | E4: 251052 | F4: 24-0718 | G4: Pfizer B41 PSPW & RO System Upgrade - Concrete | H4: 11/19/2024 | I4: 4/28/2025 | J4: 163000 | K4: Portage, MI | L4: CON | M4: Greg Klem | N4: 160800 | O4: 23000 | P4: 942 | R4: 103 | S4: 2716 | T4: 610 | V4: 368 | W4: 978 | X4: 23450 | Y4: 4 | Z4: 30319 | AA4: 264 | AB4: 35236 | AC4: 22% | AD4: The Austin Company - 0 | AE4: 882 | AF4: 147726 | AG4: 24019 | AH4: 171745 | AI4: 14% | AJ4: Open | AK4: 45717 | AM4: 0 | AV4: =IF(A4="Awarded",IFERROR((N4-J4)/J4,"-"),"-") -> -0.013496933
A5: Awarded | B5: CCI Southeast MI | C5: Other | D5: 11 | E5: 251040 | F5: 24-0544 | G5: Woodland Meadows RNG expansion | H5: 11/27/2024 | I5: 4/28/2025 | J5: 1970500 | K5: Wayne, MI | L5: CON | M5: Farzan Rafieyan-Esfahani | N5: 1970500 | O5: 178822 | P5: 10020 | Q5: Revised post bid pricing was submitted to Ameresco on February 20th, 2025 | R5: 2974 | S5: 27945 | T5: 7460 | V5: 2560 | W5: 10020 | X5: 178822 | Y5: 16 | Z5: 202932 | AA5: 1760 | AB5: 255082 | AC5: 13% | AD5: Ameresco - 0 | AE5: 12383 | AF5: 2061537 | AG5: 53571 | AH5: 2115108 | AI5: 2.5% | AJ5: Open | AK5: 45689 | AM5: 0 | AV5: =IF(A5="Awarded",IFERROR((N5-J5)/J5,"-"),"-") -> 0
A6: Awarded | B6: CCI Central MI | C6: Industrial/Power | D6: 12 | E6: 251100 | F6: 24-0792 | G6: Pfizer B41 LSS Crisaborole Mfg | H6: 12/10/2024 | I6: 7/9/2025 | J6: 239000 | K6: Kalamazoo, MI | L6: CON | M6: Dave Deller | N6: 239000 | O6: 20000 | P6: 1357 | R6: 54 | S6: 1390 | T6: 1095 | V6: 262 | W6: 1357 | X6: 20000 | Y6: 4 | Z6: 17087 | AA6: 0 | AB6: 30243 | AC6: 13% | AD6: The Austin Company - 0 | AE6: 2542 | AF6: 346585 | AG6: 139045 | AH6: 485630 | AI6: 28.6% | AJ6: Open | AK6: 45809 | AM6: 0 | AV6: =IF(A6="Awarded",IFERROR((N6-J6)/J6,"-"),"-") -> 0
A7: Awarded | B7: CCI Central MI | C7: Industrial/Power | D7: 12 | F7: 25-1108 | G7: MSU CHP BP4 Structural Concrete | H7: 12/9/2025 | I7: 1/12/2026 | J7: 2897000 | K7: East Lansing, MI | L7: CON | M7: Greg Klem | N7: 2778900 | O7: 189697 | P7: 14621 | R7: 4200 | S7: 35923 | T7: 10468 | V7: 5164 | W7: 15632 | X7: 190423 | Y7: 22 | Z7: 376158 | AA7: 2840 | AB7: 505832 | AC7: 17% | AD7: Granger Construction Company - 0 | AM7: 0 | AN7: 166600 | AV7: =IF(A7="Awarded",IFERROR((N7-J7)/J7,"-"),"-") -> -0.04076631
A8: Open | B8: CCI Central MI | C8: Other | D8: 1 | F8: 26-0009 | G8: GM LGR - Switch House/ Yard , Shipping Yard | H8: 1/8/2026 | J8: 1680368 | K8: Lansing, MI | L8: CON | M8: Tucker Dye | R8: 2375 | T8: 6762 | V8: 2148 | W8: 8910 | X8: 149805 | Y8: 20 | Z8: 217951 | AA8: 0 | AB8: 267796 | AC8: 16% | AD8: Walbridge - 0 | AM8: 0 | AN8: 49559 | AV8: =IF(A8="Awarded",IFERROR((N8-J8)/J8,"-"),"-") -> -
A9: Closed | B9: CCI Central MI | C9: Government | D9: 1 | F9: 26-0008 | G9: Lansing Fire Station No. 8 - Site and Structural Concrete | H9: 1/8/2026 | J9: 438000 | K9: Lansing, MI | L9: CON | M9: Greg Klem | Q9: Alternate 1 - Add $128,000 Alternate 2 - Add $4,000 | R9: 226 | S9: 6633 | T9: 1216 | V9: 1098 | W9: 2314 | X9: 37851 | Y9: 15 | Z9: 76877 | AA9: 720 | AB9: 103226 | AC9: 24% | AD9: The Christman Company - 0 | AM9: 0 | AN9: 70162 | AV9: =IF(A9="Awarded",IFERROR((N9-J9)/J9,"-"),"-") -> -
A10: Closed | B10: CCI Southeast MI | C10: Industrial/Power | D10: 1 | F10: 26-0034 | G10: GM Warren Tech Center Mazak Installation | H10: 1/14/2026 | J10: 93000 | K10: Warren, MI | L10: CON | M10: Dave Deller | R10: 0 | S10: 0 | T10: 356 | V10: 176 | W10: 532 | X10: 9000 | Y10: 4 | Z10: 26800 | AA10: 144 | AB10: 28061 | AC10: 30% | AD10: International Industrial Contracting Corp - 0 | AM10: 0 | AN10: 2541 | AV10: =IF(A10="Awarded",IFERROR((N10-J10)/J10,"-"),"-") -> -
A11: Open | B11: CCI Southeast MI | C11: Industrial/Power | D11: 1 | F11: 26-0025 | G11: The Barn - Warehouse | H11: 1/15/2026 | J11: 1747000 | K11: Saline, MI | L11: CON | M11: Joseph Leone | R11: 3461 | S11: 101806 | T11: 6267 | V11: 1394 | W11: 7661 | X11: 147151 | Y11: 12 | Z11: 151738 | AA11: 1146 | AB11: 218298 | AC11: 12% | AD11: La - 0 | AM11: 0 | AN11: 109099 | AV11: =IF(A11="Awarded",IFERROR((N11-J11)/J11,"-"),"-") -> -
A12: Open | B12: CCI Southeast MI | C12: Industrial/Power | D12: 1 | F12: 26-0026 | G12: The Barn - OPS Center | H12: 1/15/2026 | J12: 764000 | K12: Saline, MI | L12: CON | M12: Joseph Leone | R12: 1012 | S12: 39860 | T12: 2948 | V12: 1124 | W12: 4072 | X12: 79128 | Y12: 10 | Z12: 103541 | AA12: 832 | AB12: 148906 | AC12: 19% | AD12: La Salle - 0 | AM12: 0 | AN12: 42407 | AV12: =IF(A12="Awarded",IFERROR((N12-J12)/J12,"-"),"-") -> -
A13: Open | B13: CCI Southeast MI | C13: Other | D13: 1 | F13: 26-0031 | G13: Pinnacle Distribution Center Concrete | H13: 1/15/2026 | J13: 6277000 | K13: Romulus, MI | L13: CON | M13: Dave Deller | R13: 14474 | S13: 549916 | T13: 16748 | V13: 3888 | W13: 20636 | X13: 405000 | Y13: 24 | Z13: 329192 | AA13: 2496 | AB13: 561432 | AC13: 9% | AD13: Co - 0 Brinkmann - 0 Co;Brinkmann - 0 | AM13: 0 | AN13: 343432 | AV13: =IF(A13="Awarded",IFERROR((N13-J13)/J13,"-"),"-") -> -
A14: Open | B14: CCI Southeast MI | C14: Other | D14: 1 | F14: 26-0051 | G14: Project Lion - Wash Water Recycle System | H14: 1/16/2026 | J14: 320000 | K14: Detroit, MI | L14: CON | M14: Tucker Dye | R14: 330 | T14: 1358 | W14: 1358 | X14: 40341 | Y14: 4 | Z14: 46604 | AA14: 0 | AB14: 58051 | AC14: 18% | AD14: Shafer Redi - Mix - 0 | AM14: 0 | AN14: 42023 | AV14: =IF(A14="Awarded",IFERROR((N14-J14)/J14,"-"),"-") -> -
A15: Open | B15: CCI West Michigan | C15: Other | D15: 1 | F15: 26-0061 | G15: Amtrak Battle Creek Concrete | H15: 1/20/2026 | J15: 565500 | K15: Battle Creek, MI | L15: CON | M15: Greg Klem | P15: 0 | R15: 241 | S15: 6606 | T15: 2118 | V15: 2004 | W15: 4122 | X15: 68157 | Y15: 10 | Z15: 141026 | AA15: 880 | AB15: 176375 | AC15: 31% | AD15: George Allen Construction - 0 Krische Construction, Inc. - 0 Granite Construction Inc. - 0 | AM15: 0 | AN15: 32032 | AV15: =IF(A15="Awarded",IFERROR((N15-J15)/J15,"-"),"-") -> -
A16: Awarded | B16: CCI Southeast MI | C16: Industrial/Power | D16: 1 | E16: 251090 | F16: 25-0439 | G16: Woodland Meadows Culvert Concrete | H16: 1/8/2025 | I16: 5/22/2025 | J16: 243600 | K16: Van Buren Twp, MI | L16: CON | M16: Dave Deller | N16: 243600 | O16: 29760 | P16: 1176 | R16: 503 | S16: 14320 | T16: 876 | V16: 300 | W16: 1176 | X16: 29760 | Y16: 4 | Z16: 21171 | AA16: 256 | AB16: 23848 | AC16: 10% | AD16: D&R Earthmoving, LLC - 0 | AE16: 1385.5 | AF16: 230524 | AG16: 33376 | AH16: 263900 | AI16: 12.6% | AJ16: Open | AK16: 45778 | AM16: 0 | AN16: 11751 | AV16: =IF(A16="Awarded",IFERROR((N16-J16)/J16,"-"),"-") -> 0
A17: Closed | B17: CCI Southeast MI | C17: Historic Preservation | D17: 1 | F17: 25-0026 | G17: HFE Powerhouse Garage Pavilion Phase 2 - WC10 Concrete | H17: 1/15/2025 | J17: 1227000 | K17: Dearborn, MI | L17: CON | M17: Greg Klem | R17: 393 | S17: 11100 | T17: 4344 | V17: 2090 | W17: 6434 | X17: 129485 | Y17: 12 | Z17: 148602 | AA17: 1536 | AB17: 187322 | AC17: 15% | AD17: The Christman Company - 0 | AM17: 0 | AV17: =IF(A17="Awarded",IFERROR((N17-J17)/J17,"-"),"-") -> -
A18: Closed | B18: CCI Central MI | C18: Industrial/Power | D18: 1 | F18: 25-0069 | G18: Pfizer B225 Substation Reliability Expansion Concrete | H18: 1/24/2025 | J18: 157000 | K18: Portage, MI | L18: CON | M18: Greg Klem | R18: 101 | S18: 2600 | T18: 767 | V18: 456 | W18: 1223 | X18: 20501 | Y18: 4 | Z18: 33516 | AA18: 272 | AB18: 45400 | AC18: 29% | AD18: The Austin Company - 0 | AM18: 0 | AV18: =IF(A18="Awarded",IFERROR((N18-J18)/J18,"-"),"-") -> -
A19: Closed | B19: CCI Central MI | C19: Residential/ Housing | D19: 1 | F19: 25-0088 | G19: Tower on Grand | H19: 1/30/2025 | J19: 24497000 | K19: Lansing, MI | L19: CON | M19: Dave Deller | R19: 15580 | S19: 328652 | T19: 91256 | V19: 22300 | W19: 113556 | X19: 1800000 | Y19: 78 | Z19: 1971510 | AA19: 12792 | AB19: 2688042 | AC19: 11% | AD19: The Christman Company - 0 | AM19: 0 | AV19: =IF(A19="Awarded",IFERROR((N19-J19)/J19,"-"),"-") -> -
A20: Closed | B20: CCI Central MI | C20: Industrial/Power | D20: 1 | F20: 25-0087 | G20: Lansing Ave Pump Station and EQ Basin | H20: 1/30/2025 | J20: 8997000 | K20: Lansing, MI | L20: CON | M20: Dave Deller | R20: 7827 | S20: 55000 | T20: 20612 | V20: 10308 | W20: 30920 | X20: 997000 | Y20: 40 | Z20: 947600 | AA20: 5760 | AB20: 1491200 | AC20: 17% | AD20: FH Paschen - 0 Weiss - 0 FH Paschen;Weiss;FH Paschen;Weiss - 0 | AM20: 0 | AV20: =IF(A20="Awarded",IFERROR((N20-J20)/J20,"-"),"-") -> -
A21: Closed | B21: CCI Central MI | C21: Industrial/Power | D21: 2 | F21: 25-0137 | G21: Project Wolverine | H21: 2/14/2025 | J21: 6857000 | K21: Coldwater, MI | L21: CON | M21: Dave Deller | R21: 8522 | S21: 170000 | T21: 26297 | V21: 11096 | W21: 37393 | X21: 650000 | Y21: 40 | Z21: 800849 | AA21: 6160 | AB21: 1182911 | AC21: 17% | AD21: Gray Construction - 0 | AM21: 0 | AV21: =IF(A21="Awarded",IFERROR((N21-J21)/J21,"-"),"-") -> -
A22: Awarded | B22: CCI Southeast MI | C22: Industrial/Power | D22: 2 | E22: 251069 | F22: 25-0247 | G22: Jackson Tower Renovation | H22: 2/14/2025 | I22: 4/9/2025 | J22: 71284 | K22: Jackson, MI | L22: CON | M22: Farzan Rafieyan-Esfahani | N22: 71284 | O22: 10095 | P22: 450 | Q22: Bid was submitted via email to W.J. O'Neil on February 13th by Sean Webber on my behalf. | R22: 22 | T22: 326 | V22: 124 | W22: 450 | X22: 10095 | Y22: 2 | Z22: 8156 | AA22: 80 | AC22: 0% | AD22: W.J. O'Neil - 0 | AE22: 947 | AF22: 114591 | AG22: 11382 | AH22: 125973 | AI22: 9% | AJ22: Open | AK22: 45748 | AM22: 0 | AV22: =IF(A22="Awarded",IFERROR((N22-J22)/J22,"-"),"-") -> 0
A23: Closed | B23: CCI Southeast MI | C23: Other | D23: 2 | F23: 25-0153 | G23: WM Leachate Tank Concrete | H23: 2/21/2025 | J23: 57000 | K23: Van Buren, MI | L23: CON | M23: Greg Klem | R23: 71 | S23: 1640 | T23: 262 | V23: 98 | W23: 360 | X23: 10435 | Y23: 1 | Z23: 6893 | AA23: 80 | AB23: 9041 | AC23: 16% | AD23: D&R Earthmoving, LLC - 0 | AM23: 0 | AV23: =IF(A23="Awarded",IFERROR((N23-J23)/J23,"-"),"-") -> -
A24: Closed | B24: CCI Central MI | C24: Other | D24: 2 | F24: 25-0157 | G24: Site Concrete - Consumers Energy Lansing 9 | H24: 2/24/2025 | J24: 437000 | K24: Lansing, MI | L24: CON | M24: Ethan Conlan | R24: 400 | S24: 18000 | T24: 1666 | V24: 704 | W24: 2370 | X24: 49392 | Y24: 8 | Z24: 0 | AA24: 512 | AB24: 60278 | AC24: 14% | AD24: Consumers Energy - 0 | AM24: 0 | AV24: =IF(A24="Awarded",IFERROR((N24-J24)/J24,"-"),"-") -> -
A25: Awarded | B25: CCI Central MI | C25: Industrial/Power | D25: 2 | E25: 251048 | F25: 25-0160 | G25: Switch GRR02 Slab Trench Drains | H25: 2/26/2025 | I25: 3/6/2025 | J25: 880700 | K25: Caledonia, MI | L25: CON | M25: Greg Klem | N25: 846100 | O25: 76793 | P25: 4932 | R25: 220 | S25: 7690 | T25: 4256 | V25: 1012 | W25: 5268 | X25: 89823 | Y25: 10 | Z25: 90043 | AA25: 880 | AB25: 96033 | AC25: 11% | AD25: The Christman Company - 0 | AE25: 8624.75 | AF25: 888171 | AG25: 159811 | AH25: 1047982 | AI25: 15.2% | AJ25: Open | AK25: 45717 | AM25: 0 | AV25: =IF(A25="Awarded",IFERROR((N25-J25)/J25,"-"),"-") -> -0.039286931
A26: Awarded | B26: CCI Southeast MI | C26: Elem/High School | D26: 2 | E26: 251088 | F26: 25-0163 | G26: AAPS Thurston - WC05A Foundations | H26: 2/27/2025 | I26: 5/14/2025 | J26: 1879000 | K26: Ann Arbor, MI | L26: CON | M26: Greg Klem | N26: 1879000 | O26: 160107 | P26: 9022 | R26: 1986 | S26: 60000 | T26: 6718 | V26: 2304 | W26: 9022 | X26: 160107 | Y26: 16 | Z26: 170778 | AA26: 1536 | AB26: 227416 | AC26: 12% | AD26: The Christman Company - 0 | AE26: 9911.5 | AF26: 2190475 | AG26: -299630 | AH26: 1890845 | AI26: -15.8% | AJ26: Open | AK26: 45778 | AM26: 0 | AV26: =IF(A26="Awarded",IFERROR((N26-J26)/J26,"-"),"-") -> 0
A27: Closed | B27: CCI Southeast MI | C27: Elem/High School | D27: 2 | F27: 25-0164 | G27: AAPS Thurston WC05B Site Concrete | H27: 2/27/2025 | J27: 1069000 | K27: Ann Arbor, MI | L27: CON | M27: Greg Klem | R27: 1985 | S27: 73740 | T27: 3946 | V27: 1602 | W27: 5548 | X27: 110168 | Y27: 13 | Z27: 118161 | AA27: 1248 | AB27: 171869 | AC27: 16% | AD27: The Christman Company - 0 | AM27: 0 | AV27: =IF(A27="Awarded",IFERROR((N27-J27)/J27,"-"),"-") -> -
A28: Closed | B28: CCI Southeast MI | C28: Elem/High School | D28: 2 | F28: 25-0165 | G28: AAPS Thurston WC10 Interior Concrete Flatwork | H28: 2/27/2025 | J28: 1253000 | K28: Ann Arbor, MI | L28: CON | M28: Greg Klem | R28: 1107 | S28: 60000 | T28: 3392 | V28: 1128 | W28: 4520 | X28: 101110 | Y28: 8 | Z28: 83989 | AA28: 720 | AB28: 132088 | AC28: 11% | AD28: The Christman Company - 0 | AM28: 0 | AV28: =IF(A28="Awarded",IFERROR((N28-J28)/J28,"-"),"-") -> -
A29: Awarded | B29: CCI Central MI | C29: Government | D29: 2 | E29: 251073 | F29: 25-0170 | G29: Consumers Energy - City Gate - H-2 Highland | H29: 2/28/2025 | I29: 5/21/2025 | J29: 181458 | K29: Highland, MI | L29: CON | M29: Farzan Rafieyan-Esfahani | N29: 181458 | P29: 0 | R29: 174 | T29: 1077 | V29: 340 | W29: 1417 | X29: 23384 | Y29: 4 | Z29: 22830 | AA29: 288 | AB29: 33371 | AC29: 18% | AD29: Henkels & McCoy - 0 | AE29: 1268 | AF29: 155091 | AG29: 39448 | AH29: 194539 | AI29: 20.3% | AJ29: Hard Closed | AK29: 45748 | AL29: 45901 | AM29: 21 | AV29: =IF(A29="Awarded",IFERROR((N29-J29)/J29,"-"),"-") -> 0
A30: Awarded | B30: CCI Central MI | C30: Government | D30: 2 | E30: 251086 | F30: 25-0167 | G30: Consumers Energy - City Gate - B-1 Bancroft | H30: 2/28/2025 | I30: 5/28/2025 | J30: 123336 | K30: Byron, MI | L30: CON | M30: Farzan Rafieyan-Esfahani | N30: 123336 | O30: 16182 | P30: 1026 | Q30: Bid was submitted to Henkels & McCoy on February 28th via email. | R30: 70 | T30: 686 | V30: 340 | W30: 1026 | X30: 16182 | Y30: 4 | Z30: 22830 | AA30: 288 | AB30: 32696 | AC30: 27% | AD30: Henkels & McCoy - 0 | AE30: 664.5 | AF30: 80872 | AG30: 47128 | AH30: 128000 | AI30: 36.8% | AJ30: Open | AK30: 45778 | AM30: 0 | AV30: =IF(A30="Awarded",IFERROR((N30-J30)/J30,"-"),"-") -> 0
A31: Awarded | B31: CCI Central MI | C31: Government | D31: 2 | E31: 251078 | F31: 25-0168 | G31: Consumers Energy - City Gate - F-4 Flint | H31: 2/28/2025 | I31: 5/28/2025 | J31: 167188 | K31: Flint, MI | L31: CON | M31: Farzan Rafieyan-Esfahani | N31: 167188 | O31: 20575 | P31: 1166 | Q31: Bid was submitted to Henkels & McCoy on February 28th via email. | R31: 82 | T31: 826 | V31: 340 | W31: 1166 | X31: 20575 | Y31: 4 | Z31: 22830 | AA31: 288 | AB31: 33972 | AC31: 20% | AD31: Henkels & McCoy - 0 | AE31: 718.5 | AF31: 106093 | AG31: 65907 | AH31: 172000 | AI31: 38.3% | AJ31: Open | AK31: 45778 | AM31: 0 | AV31: =IF(A31="Awarded",IFERROR((N31-J31)/J31,"-"),"-") -> 0
A32: Closed | B32: CCI Central MI | C32: Government | D32: 2 | F32: 25-0169 | G32: Consumers Energy - City Gate - H-1 Hanover Horton | H32: 2/28/2025 | J32: 113310 | K32: Horton, MI | L32: CON | M32: Farzan Rafieyan-Esfahani | R32: 70 | T32: 612 | V32: 268 | W32: 880 | X32: 14511 | Y32: 3 | Z32: 17830 | AA32: 216 | AB32: 26998 | AC32: 24% | AD32: Henkels & McCoy - 0 | AM32: 0 | AV32: =IF(A32="Awarded",IFERROR((N32-J32)/J32,"-"),"-") -> -
A33: Closed | B33: Out of Region | C33: Industrial/Power | D33: 3 | F33: 25-0200 | G33: TC Energy TVA Rewheel Gas Cooler Project | H33: 3/10/2025 | J33: 738949 | K33: Hartsville, TN | L33: CON | M33: Frank Duff | R33: 410 | T33: 1753 | V33: 1436 | W33: 3189 | X33: 82811 | Y33: 12 | Z33: 104728 | AA33: 1376 | AB33: 212851 | AC33: 29% | AD33: Michels Pipeline, Inc. - 0 | AM33: 0 | AV33: =IF(A33="Awarded",IFERROR((N33-J33)/J33,"-"),"-") -> -
A34: Closed | B34: CCI Southeast MI | C34: Industrial/Power | D34: 3 | F34: 25-0196 | G34: Monroe WWTP | H34: 3/10/2025 | J34: 157100 | K34: Monroe, MI | L34: CON | M34: Greg Klem | R34: 14 | S34: 0 | T34: 464 | V34: 886 | W34: 1350 | X34: 22318 | Y34: 6 | Z34: 67734 | AA34: 656 | AB34: 75241 | AC34: 48% | AD34: FH Paschen - 0 | AM34: 0 | AV34: =IF(A34="Awarded",IFERROR((N34-J34)/J34,"-"),"-") -> -
A35: Closed | B35: CCI Central MI | C35: Health Care | D35: 3 | F35: 25-0283 | G35: Corewell Health Residency Housing | H35: 3/19/2025 | J35: 9367000 | K35: Grand Rapids, MI | L35: CON | M35: Dave Deller | R35: 13286 | S35: 181334 | T35: 24494 | V35: 9666 | W35: 34160 | X35: 720000 | Y35: 34 | Z35: 638321 | AA35: 5440 | AB35: 1493143 | AC35: 16% | AD35: Christman/ Spesh - 0 | AM35: 0 | AV35: =IF(A35="Awarded",IFERROR((N35-J35)/J35,"-"),"-") -> -
A36: Closed | B36: CCI Southeast MI | C36: Retail | D36: 3 | F36: 25-0246 | G36: Korex Addition | H36: 3/27/2025 | J36: 3317000 | K36: Wixom, MI | L36: CON | M36: Ethan Conlan | R36: 6726 | S36: 237000 | T36: 15836 | V36: 3518 | W36: 19354 | X36: 322266 | Y36: 19 | Z36: 259862 | AA36: 2792 | AB36: 334381 | AC36: 10% | AD36: Brinkmann - 0 | AM36: 0 | AV36: =IF(A36="Awarded",IFERROR((N36-J36)/J36,"-"),"-") -> -
A37: Closed | B37: CCI Central MI | C37: Government | D37: 4 | F37: 25-0281 | G37: Lansing City Hall BC 003B Foundations | H37: 4/2/2025 | J37: 449000 | K37: Lansing, MI | L37: CON | M37: Dave Deller | R37: 563 | S37: 26000 | T37: 1515 | V37: 1072 | W37: 2587 | X37: 42000 | Y37: 6 | Z37: 83906 | AA37: 672 | AB37: 83906 | AC37: 19% | AD37: Cl - 0 | AM37: 0 | AV37: =IF(A37="Awarded",IFERROR((N37-J37)/J37,"-"),"-") -> -
A38: Closed | B38: CCI Southeast MI | C38: Retail | D38: 4 | F38: 25-0282 | G38: QMI 1 PADDC Concrete | H38: 4/2/2025 | J38: 237000 | K38: Hazel Park, MI | L38: CON | M38: Dave Deller | R38: 100 | S38: 0 | T38: 827 | V38: 528 | W38: 1355 | X38: 25000 | Y38: 4 | Z38: 34446 | AA38: 416 | AB38: 49586 | AC38: 21% | AD38: KPRS Construction Services - 0 | AM38: 0 | AV38: =IF(A38="Awarded",IFERROR((N38-J38)/J38,"-"),"-") -> -
A39: Awarded | B39: CCI Central MI | C39: Government | D39: 4 | E39: 251084 | F39: 25-0280 | G39: Lansing City Hall BC003A Flatwork | H39: 4/2/2025 | I39: 5/16/2025 | J39: 543000 | K39: Lansing, MI | L39: CON | M39: Dave Deller | N39: 543000 | O39: 50000 | P39: 2993 | R39: 563 | S39: 65000 | T39: 2561 | V39: 432 | W39: 2993 | X39: 50000 | Y39: 4 | Z39: 26361 | AA39: 232 | AB39: 37940 | AC39: 7% | AD39: Clark Lansing - 0 | AE39: 3013.5 | AF39: 565850 | AG39: 87282 | AH39: 653132 | AI39: 13.4% | AJ39: Open | AK39: 45778 | AM39: 0 | AV39: =IF(A39="Awarded",IFERROR((N39-J39)/J39,"-"),"-") -> 0
A40: Closed | B40: CCI Central MI | C40: Office | D40: 4 | F40: 25-0277 | G40: Zoetis B248 Cafe Upgrade | H40: 4/2/2025 | J40: 166922 | K40: Kalamazoo, MI | L40: CON | M40: Farzan Rafieyan-Esfahani | R40: 144 | S40: 4715 | T40: 815 | V40: 284 | W40: 1099 | X40: 24089 | Y40: 4 | Z40: 19826 | AA40: 224 | AB40: 19826 | AC40: 12% | AD40: The Austin Company - 0 | AM40: 0 | AV40: =IF(A40="Awarded",IFERROR((N40-J40)/J40,"-"),"-") -> -
A41: Closed | B41: CCI Central MI | C41: Government | D41: 4 | F41: 25-0290 | G41: Consumers Energy - Jackson Hart (J-1) City Gate | H41: 4/7/2025 | J41: 357402 | K41: Jackson , MI | L41: CON | M41: Farzan Rafieyan-Esfahani | Q41: Bid was submitted via email to Henkels & McCoy and separate bid number was submitted to Veterans Utility Services. | R41: 141 | S41: 2295 | T41: 1449 | V41: 536 | W41: 1985 | X41: 32365 | Y41: 6 | Z41: 35299 | AA41: 496 | AB41: 54756 | AC41: 15% | AD41: Henkels & McCoy - 0 | AM41: 0 | AV41: =IF(A41="Awarded",IFERROR((N41-J41)/J41,"-"),"-") -> -
A42: Awarded | B42: CCI Central MI | C42: Government | D42: 4 | E42: 251082 | F42: 25-0291 | G42: Consumers Energy - Riverside (R-4) City Gate | H42: 4/7/2025 | I42: 5/21/2025 | J42: 547000 | K42: Falmouth, MI | L42: CON | M42: Farzan Rafieyan-Esfahani | N42: 174000 | O42: 17567 | P42: 1054 | Q42: Bid was submitted to Henkels & McCoy via email. A separate email was sent to Veteran's Utility Services. Contract value changed to $ 174,000 after removing earthwork scope of work. | R42: 84 | S42: 1322 | T42: 1702 | V42: 568 | W42: 2270 | X42: 49799 | Y42: 8 | Z42: 38979 | AA42: 528 | AB42: 96583 | AC42: 18% | AD42: Henkels & McCoy - 0 | AE42: 928.5 | AF42: 106839 | AG42: 83886 | AH42: 190725 | AI42: 44% | AJ42: Hard Closed | AK42: 45778 | AL42: 45901 | AM42: 17 | AV42: =IF(A42="Awarded",IFERROR((N42-J42)/J42,"-"),"-") -> -0.68190128
A43: Closed | B43: CCI Central MI | C43: Government | D43: 4 | F43: 25-0292 | G43: Consumers Energy - Gerwoude City Gate (M-4) | H43: 4/7/2025 | J43: 77262 | K43: McBain, MI | L43: CON | M43: Farzan Rafieyan-Esfahani | Q43: Bid was submitted to Henkels & McCoy via email. A separate email was sent to Veteran's Utility Services. | R43: 10 | S43: 87 | T43: 276 | V43: 108 | W43: 384 | X43: 7289 | Y43: 2 | Z43: 7144 | AA43: 80 | AB43: 21538 | AC43: 28% | AD43: Henkels & McCoy - 0 | AM43: 0 | AV43: =IF(A43="Awarded",IFERROR((N43-J43)/J43,"-"),"-") -> -
A44: Closed | B44: CCI Central MI | C44: Government | D44: 4 | F44: 25-0293 | G44: Consumers Energy - Stoney Corner & Burkette Rd | H44: 4/7/2025 | J44: 71293 | K44: McBain, MI | L44: CON | M44: Farzan Rafieyan-Esfahani | Q44: Bid was submitted to Henkels & McCoy via email. A separate email was sent to Veteran's Utility Services. | R44: 7 | S44: 87 | T44: 246 | V44: 98 | W44: 344 | X44: 6627 | Y44: 2 | Z44: 6579 | AA44: 80 | AB44: 22433 | AC44: 31% | AD44: Henkels & McCoy - 0 | AM44: 0 | AV44: =IF(A44="Awarded",IFERROR((N44-J44)/J44,"-"),"-") -> -
A45: Closed | B45: CCI Central MI | C45: Government | D45: 4 | F45: 25-0406 | G45: Grand Ledge WWTP CIP Concrete | H45: 4/8/2025 | J45: 5579000 | K45: Grand Ledge, MI | L45: CON | M45: Greg Klem | R45: 5102 | S45: 33123 | T45: 17832 | V45: 8124 | W45: 25956 | X45: 502354 | Y45: 34 | Z45: 605281 | AA45: 11120 | AB45: 890723 | AC45: 16% | AD45: - 0 | AM45: 0 | AN45: 335235 | AV45: =IF(A45="Awarded",IFERROR((N45-J45)/J45,"-"),"-") -> -
A46: Closed | B46: CCI Central MI | C46: Government | D46: 4 | F46: 25-0340 | G46: 30th Street Valve Site | H46: 4/22/2025 | J46: 17021 | K46: Hamilton, MI | L46: CON | M46: Farzan Rafieyan-Esfahani | Q46: Bid was submitted via email to Andrew Trainor (Veteran's Utility Services) | R46: 4 | S46: 124 | T46: 56 | V46: 40 | W46: 96 | X46: 1678 | Y46: 1 | Z46: 2284 | AA46: 16 | AB46: 9307 | AC46: 55% | AD46: Veteran's Utility Service LLC - 0 | AM46: 0 | AV46: =IF(A46="Awarded",IFERROR((N46-J46)/J46,"-"),"-") -> -
A47: Closed | B47: CCI Central MI | C47: Government | D47: 4 | F47: 25-0341 | G47: Monterey 23 TMS Interchange | H47: 4/22/2025 | J47: 26411 | K47: Hopkins, MI | L47: CON | M47: Farzan Rafieyan-Esfahani | Q47: Bid was submitted to Andrew Trainor (Veteran's Utility Services LLC) via email. | R47: 8 | S47: 110 | T47: 114 | V47: 40 | W47: 154 | X47: 2706 | Y47: 1 | Z47: 1869 | AA47: 16 | AB47: 10218 | AC47: 39% | AD47: Veteran's Utility Services - 0 | AM47: 0 | AV47: =IF(A47="Awarded",IFERROR((N47-J47)/J47,"-"),"-") -> -
A48: Closed | B48: CCI Southeast MI | C48: Elem/High School | D48: 4 | F48: 25-0351 | G48: Ann Arbor Public School - NOC Relocation | H48: 4/24/2025 | J48: 145367 | K48: Ann Arbor , MI | L48: CON | M48: Farzan Rafieyan-Esfahani | Q48: Bid was submitted to The Christman Company via Building Connected. | R48: 67 | S48: 1757 | T48: 602 | V48: 408 | W48: 1010 | X48: 23753 | Y48: 3 | Z48: 27713 | AA48: 272 | AB48: 35829 | AC48: 25% | AD48: The Christman Company - 0 | AM48: 0 | AV48: =IF(A48="Awarded",IFERROR((N48-J48)/J48,"-"),"-") -> -
A49: Closed | B49: CCI Central MI | C49: Parking Deck | D49: 4 | F49: 25-0358 | G49: Kalamazoo Event Center Parking Deck | H49: 4/25/2025 | J49: 3987000 | K49: Kalamazoo, MI | L49: CON | M49: Greg Klem | R49: 4629 | S49: 136715 | T49: 15042 | V49: 5920 | W49: 20962 | X49: 282710 | Y49: 34 | Z49: 519771 | AA49: 4540 | AB49: 700356 | AC49: 18% | AD49: Barton Malow/CSM - 0 | AM49: 0 | AV49: =IF(A49="Awarded",IFERROR((N49-J49)/J49,"-"),"-") -> -
A50: Closed | B50: CCI Southeast MI | C50: Industrial/Power | D50: 4 | F50: 25-0568 | G50: Carleton Farms Landfill Leachate Tank | H50: 4/29/2025 | J50: 339000 | K50: Carleton, MI | L50: CON | M50: Dave Deller | R50: 335 | S50: 4900 | T50: 1156 | V50: 888 | W50: 2044 | X50: 33000 | Y50: 6 | Z50: 60748 | AA50: 528 | AB50: 76714 | AC50: 23% | AD50: D&R Earthmoving, LLC - 0 | AM50: 0 | AN50: 17686 | AV50: =IF(A50="Awarded",IFERROR((N50-J50)/J50,"-"),"-") -> -
A51: Closed | B51: CCI Central MI | C51: Sports / Event Venues | D51: 5 | F51: 25-0395 | G51: CD Arena Kalamazoo Event Center - BP 4-04 Slab on Grade, Elevated Slabs, Steps | H51: 5/7/2025 | J51: 10297000 | K51: Kalamazoo, MI | L51: CON | M51: Greg Klem | R51: 9700 | S51: 591000 | T51: 32256 | V51: 7318 | W51: 39574 | X51: 814399 | Y51: 39 | Z51: 981794 | AA51: 4680 | AB51: 981794 | AC51: 10% | AD51: Barton Malow/CSM - 0 | AM51: 0 | AV51: =IF(A51="Awarded",IFERROR((N51-J51)/J51,"-"),"-") -> -
A52: Closed | B52: CCI Central MI | C52: Other | D52: 5 | F52: 25-0473 | G52: Harris Compressor Station | H52: 5/8/2025 | J52: 427720 | K52: Olivet, MI | L52: CON | M52: Farzan Rafieyan-Esfahani | Q52: Henkles requested to remove Bollards ($ 10,500 deduct) from scope of work and to add Epoxy Grout under Compressor equipment ($ 35,500 add). | R52: 260 | S52: 8200 | T52: 1754 | V52: 716 | W52: 2470 | X52: 48947 | Y52: 8 | Z52: 48917 | AA52: 608 | AB52: 73434 | AC52: 17% | AD52: Henkels & McCoy - 0 | AM52: 0 | AN52: 54441 | AV52: =IF(A52="Awarded",IFERROR((N52-J52)/J52,"-"),"-") -> -
A53: Closed | B53: CCI Southeast MI | C53: Government | D53: 5 | F53: 25-0454 | G53: Belle Isle Aquarium - Concrete | H53: 5/8/2025 | J53: 465000 | K53: Detroit, MI | L53: CON | M53: Frank Duff | R53: 464 | T53: 1606 | V53: 888 | W53: 2494 | X53: 42274 | Y53: 8 | Z53: 61272 | AA53: 672 | AB53: 99401 | AC53: 21% | AD53: The Christman Company - 0 | AM53: 0 | AN53: 28357 | AV53: =IF(A53="Awarded",IFERROR((N53-J53)/J53,"-"),"-") -> -
A54: Closed | B54: CCI Southeast MI | C54: Government | D54: 5 | F54: 25-0414 | G54: Clarkston Road Development - Water Well - Foundation & Footings | H54: 5/15/2025 | J54: 72254 | K54: Oakland Township , MI | L54: CON | M54: Farzan Rafieyan-Esfahani | Q54: Bid category 3.1 was submitted to Auch Company via email. Bid will be hand-delivered to Auch Company today. | R54: 28 | S54: 121 | T54: 300 | V54: 176 | W54: 476 | X54: 10282 | Y54: 2 | Z54: 11646 | AA54: 132 | AB54: 16588 | AC54: 23% | AD54: George W. Auch Company - 0 | AM54: 0 | AN54: 5930 | AV54: =IF(A54="Awarded",IFERROR((N54-J54)/J54,"-"),"-") -> -
A55: Closed | B55: CCI Southeast MI | C55: Government | D55: 5 | F55: 25-0415 | G55: Clarkston Rd Development - Water Well - Flat Work | H55: 5/15/2025 | J55: 86159 | K55: Oakland Township, MI | L55: CON | M55: Farzan Rafieyan-Esfahani | Q55: Bid category 3.2 was submitted to Auch Company via email. Bid hard copies will be hand delivered to Auch Company today. | R55: 60 | S55: 2252 | T55: 316 | V55: 184 | W55: 500 | X55: 10080 | Y55: 2 | Z55: 12074 | AA55: 136 | AB55: 22661 | AC55: 26% | AD55: George w. Auch Company - 0 | AM55: 0 | AN55: 4502 | AV55: =IF(A55="Awarded",IFERROR((N55-J55)/J55,"-"),"-") -> -
A56: Closed | B56: Out of Region | C56: Industrial/Power | D56: 5 | F56: 25-0457 | G56: CDM Smith AES Petersburg - Concrete Foundations | H56: 5/16/2025 | J56: 1129733 | K56: Petersburg, IN | L56: CON | M56: Frank Duff | R56: 887 | T56: 2632 | V56: 1231 | W56: 3863 | X56: 102616 | Y56: 10 | Z56: 97635 | AA56: 920 | AB56: 226103 | AC56: 20% | AD56: CDM Smith - 0 | AM56: 0 | AN56: 127750 | AV56: =IF(A56="Awarded",IFERROR((N56-J56)/J56,"-"),"-") -> -
A57: Closed | B57: CCI Southeast MI | C57: Residential/ Housing | D57: 5 | F57: 25-0440 | G57: Chapter AA - FHP Team CIP Project | H57: 5/21/2025 | J57: 16122000 | K57: Ann Arbor, MI | L57: CON | M57: Dave Deller | Q57: Submitted with FH Paschen under a teaming agreement. FHP is the lead on this one. | R57: 9898 | S57: 244184 | T57: 34296 | V57: 10054 | W57: 44350 | X57: 1400997 | Y57: 48 | Z57: 1136990 | AA57: 7248 | AB57: 2384388 | AC57: 15% | AD57: J.H. Findorff & Son, Inc. - 0 | AM57: 0 | AN57: 565276 | AV57: =IF(A57="Awarded",IFERROR((N57-J57)/J57,"-"),"-") -> -
A58: Closed | B58: CCI Central MI | C58: Industrial/Power | D58: 5 | F58: 25-0496 | G58: LBWL DEP Stair Tower | H58: 5/28/2025 | J58: 459000 | K58: Lansing, MI | L58: CON | M58: Ethan Conlan | R58: 20 | S58: 212 | T58: 511 | V58: 290 | W58: 801 | X58: 30290 | Y58: 4 | Z58: 16407 | AA58: 264 | AB58: 35167 | AC58: 8% | AD58: LBWL - 0 | AM58: 0 | AN58: 16057 | AV58: =IF(A58="Awarded",IFERROR((N58-J58)/J58,"-"),"-") -> -
A59: Awarded | B59: CCI Southeast MI | C59: Health Care | D59: 5 | E59: 251106 | F59: 24-0611 | G59: Jackson Health Services - Parking Lot | H59: 5/29/2025 | I59: 7/2/2025 | J59: 117844 | K59: Jackson, MI | L59: CON | M59: Farzan Rafieyan-Esfahani | N59: 117000 | P59: 0 | Q59: Bid scope was revised based on Teams' call on May 29th, 2025. | R59: 110 | S59: 5940 | T59: 144 | V59: 120 | W59: 264 | X59: 12751 | Y59: 2 | Z59: 8495 | AA59: 128 | AB59: 16586 | AC59: 14% | AD59: Veregy - 0 | AE59: 474.5 | AF59: 142193 | AG59: 44502 | AH59: 186695 | AI59: 23.8% | AJ59: Open | AK59: 45839 | AM59: 0 | AN59: 2531 | AV59: =IF(A59="Awarded",IFERROR((N59-J59)/J59,"-"),"-") -> -0.0071620108
A60: Closed | B60: CCI Southeast MI | C60: Industrial/Power | D60: 5 | F60: 25-0463 | G60: DTE Belle River ILI Expansion | H60: 5/29/2025 | J60: 68100 | K60: China, MI | L60: CON | M60: Christian Oglesby | R60: 13 | S60: 1580 | T60: 373 | V60: 128 | W60: 501 | X60: 8200 | Y60: 0 | Z60: 0 | AA60: 80 | AB60: 10572 | AC60: 16% | AD60: Precision Pipeline - 0 | AM60: 0 | AN60: 8174 | AV60: =IF(A60="Awarded",IFERROR((N60-J60)/J60,"-"),"-") -> -
A61: Awarded | B61: CCI Central MI | C61: Industrial/Power | D61: 5 | E61: 251156 | F61: 25-0567 | G61: Pfizer Metrology Lab | H61: 5/30/2025 | I61: 8/20/2025 | J61: 108500 | K61: Kalamazoo, MI | L61: CON | M61: Dave Deller | N61: 108500 | O61: 10000 | P61: 1140 | R61: 254 | S61: 224 | T61: 812 | V61: 328 | W61: 1140 | X61: 10000 | Y61: 4 | Z61: 23063 | AA61: 256 | AB61: 18240 | AC61: 17% | AD61: The Austin Company - 0 | AE61: 917.5 | AF61: 92500 | AG61: 16005 | AH61: 108505 | AI61: 14.8% | AJ61: Open | AK61: 45931 | AM61: 0 | AN61: 9809 | AV61: =IF(A61="Awarded",IFERROR((N61-J61)/J61,"-"),"-") -> 0
A62: Closed | B62: CCI Southeast MI | C62: Residential/ Housing | D62: 6 | F62: 25-0506 | G62: The Metropolitan Ann Arbor | H62: 6/13/2025 | J62: 28897000 | K62: Ann Arbor, MI | L62: CON | M62: Dave Deller | R62: 16893 | S62: 460000 | T62: 89970 | V62: 32566 | W62: 122536 | X62: 3000000 | Y62: 58 | Z62: 3093739 | AA62: 8720 | AB62: 5055979 | AC62: 17% | AD62: Landmark Properties - 0 | AM62: 0 | AN62: 1635987 | AV62: =IF(A62="Awarded",IFERROR((N62-J62)/J62,"-"),"-") -> -
A63: Closed | B63: CCI Southeast MI | C63: Government | D63: 6 | F63: 25-0512 | G63: Lansing Public Safety - Fire Training Facility - WC 10F - Structural Concrete | H63: 6/18/2025 | J63: 868982 | K63: Lansing , MI | L63: CON | M63: Farzan Rafieyan-Esfahani | Q63: The bid was submitted to Nick Nelson (Christman Company) via email. | R63: 700 | S63: 21428 | T63: 3895 | V63: 1272 | W63: 5167 | X63: 85805 | Y63: 15 | Z63: 95770 | AA63: 1020 | AB63: 142755 | AC63: 16% | AD63: The Christman Company - 0 | AM63: 0 | AN63: 67993 | AV63: =IF(A63="Awarded",IFERROR((N63-J63)/J63,"-"),"-") -> -
A64: Closed | B64: CCI Central MI | C64: Government | D64: 6 | F64: 25-0569 | G64: Lansing City Hall BP3 Site Concrete | H64: 6/19/2025 | J64: 219000 | K64: Lansing, MI | L64: CON | M64: Dave Deller | R64: 200 | S64: 7082 | T64: 1340 | V64: 512 | W64: 1852 | X64: 25000 | Y64: 4 | Z64: 36152 | AA64: 400 | AB64: 45084 | AC64: 21% | AD64: Clark Lansing - 0 | AM64: 0 | AN64: 3550 | AV64: =IF(A64="Awarded",IFERROR((N64-J64)/J64,"-"),"-") -> -
A65: Closed | B65: CCI Central MI | C65: Industrial/Power | D65: 6 | F65: 25-0576 | G65: TransCanada South Chester Separator | H65: 6/30/2025 | J65: 395000 | K65: Johannesburg, MI | L65: CON | M65: Dave Deller | R65: 159 | T65: 1235 | V65: 1052 | W65: 2287 | X65: 34000 | Y65: 4 | Z65: 149202 | AA65: 448 | AB65: 149202 | AC65: 38% | AD65: Henkels & McCoy - 0 | AM65: 0 | AN65: 12178 | AV65: =IF(A65="Awarded",IFERROR((N65-J65)/J65,"-"),"-") -> -
A66: Closed | B66: CCI Central MI | C66: Industrial/Power | D66: 7 | F66: 25-0566 | G66: Brent Run Blower Flare | H66: 7/2/2025 | J66: 45000 | K66: Montrose, MI | L66: CON | M66: Dave Deller | R66: 30 | S66: 711 | T66: 164 | V66: 124 | W66: 288 | X66: 4000 | Y66: 2 | Z66: 9327 | AA66: 104 | AB66: 12416 | AC66: 28% | AD66: D&R Earthmoving, LLC - 0 | AM66: 0 | AN66: 3915 | AV66: =IF(A66="Awarded",IFERROR((N66-J66)/J66,"-"),"-") -> -
A67: Closed | B67: CCI Central MI | C67: Industrial/Power | D67: 7 | F67: 25-0571 | G67: Pfizer KIIP Master Substation #2 - BP 3.1 Concrete | H67: 7/7/2025 | J67: 249564 | K67: Kalamazoo, MI | L67: CON | M67: Farzan Rafieyan-Esfahani | Q67: Bid was submitted to the Austin Company via email. | R67: 233 | S67: 8519 | T67: 1208 | V67: 470 | W67: 1678 | X67: 29158 | Y67: 5 | Z67: 31107 | AA67: 400 | AB67: 51494 | AC67: 21% | AD67: The Austin Company - 0 | AM67: 0 | AN67: 16788 | AV67: =IF(A67="Awarded",IFERROR((N67-J67)/J67,"-"),"-") -> -
A68: Closed | B68: CCI Southeast MI | C68: Government | D68: 7 | F68: 25-0577 | G68: Woodland Correctional Facility Generator | H68: 7/8/2025 | J68: 33700 | K68: Whitmore Lake, MI | L68: CON | M68: Dave Deller | R68: 23 | S68: 738 | T68: 152 | V68: 104 | W68: 256 | X68: 3000 | Y68: 1 | Z68: 7869 | AA68: 80 | AB68: 9346 | AC68: 28% | AD68: The Christman Company - 0 | AM68: 0 | AN68: 1865 | AV68: =IF(A68="Awarded",IFERROR((N68-J68)/J68,"-"),"-") -> -
A69: Closed | B69: CCI Southeast MI | C69: Industrial/Power | D69: 7 | F69: 25-0587 | G69: Kalamazoo Country Club - Irrigation Building | H69: 7/10/2025 | J69: 223000 | K69: Kalamazoo, MI | L69: CON | M69: Christian Oglesby | R69: 127 | S69: 0 | T69: 950 | V69: 462 | W69: 1412 | X69: 25951 | Y69: 5 | Z69: 39300 | AA69: 352 | AB69: 75915 | AC69: 34% | AD69: CSM Group - 0 | AM69: 0 | AN69: 8963 | AV69: =IF(A69="Awarded",IFERROR((N69-J69)/J69,"-"),"-") -> -
A70: Closed | B70: CCI Southeast MI | C70: Government | D70: 7 | F70: 25-0532 | G70: Detroit Arsenal - Structural Concrete | H70: 7/10/2025 | J70: 1191500 | K70: Warren, MI | L70: CON | M70: Greg Klem | R70: 1495 | S70: 43888 | T70: 4768 | V70: 2152 | W70: 6920 | X70: 122873 | Y70: 12 | Z70: 155272 | AA70: 1344 | AB70: 190641 | AC70: 16% | AD70: Walsh Group - 0 | AM70: 0 | AN70: 63576 | AV70: =IF(A70="Awarded",IFERROR((N70-J70)/J70,"-"),"-") -> -
A71: Closed | B71: CCI Southeast MI | C71: Government | D71: 7 | F71: 25-0533 | G71: Detroit Arsenal - Site Concrete | H71: 7/10/2025 | J71: 425000 | K71: Warren, MI | L71: CON | M71: Greg Klem | R71: 780 | S71: 31787 | T71: 1469 | V71: 638 | W71: 2107 | X71: 39635 | Y71: 3 | Z71: 49184 | AA71: 448 | AB71: 70864 | AC71: 17% | AD71: Walsh Group - 0 | AM71: 0 | AN71: 17025 | AV71: =IF(A71="Awarded",IFERROR((N71-J71)/J71,"-"),"-") -> -
A72: Closed | B72: CCI Southeast MI | C72: Higher Ed | D72: 7 | F72: 25-0625 | G72: WSU Health Sciences Building BP2 - WC 10 Structural Concrete | H72: 7/18/2025 | J72: 3555000 | K72: Detroit, MI | L72: CON | M72: Greg Klem | Q72: VE Items: - Mapei Fibers ILO Resteel - Deduct $144,000 - Helix Fibers ILO Resteel - Deduct $64,000 | R72: 5020 | S72: 169565 | T72: 9842 | V72: 5012 | W72: 14854 | X72: 263690 | Y72: 26 | Z72: 360566 | AA72: 3328 | AB72: 516513 | AC72: 15% | AD72: The Christman Company - 0 | AM72: 0 | AN72: 265524 | AV72: =IF(A72="Awarded",IFERROR((N72-J72)/J72,"-"),"-") -> -
A73: Closed | B73: CCI Central MI | C73: Residential/ Housing | D73: 7 | F73: 25-0564 | G73: NMU Student Housing | H73: 7/26/2025 | J73: 2187000 | K73: Marquette, MI | L73: CON | M73: Dave Deller | R73: 1830 | S73: 38422 | T73: 6747 | V73: 3500 | W73: 10247 | X73: 200000 | Y73: 16 | Z73: 282361 | AA73: 2304 | AB73: 470461 | AC73: 22% | AD73: Stevens Construction Corp. - 0 | AM73: 0 | AN73: 157651 | AV73: =IF(A73="Awarded",IFERROR((N73-J73)/J73,"-"),"-") -> -
A74: Closed | B74: CCI Southeast MI | C74: Health Care | D74: 7 | F74: 25-0658 | G74: Lifeways-Concrete | H74: 7/30/2025 | J74: 773000 | K74: Hillsdale, MI | L74: CON | M74: Ethan Conlan | R74: 927 | S74: 39750 | T74: 5464 | V74: 1744 | W74: 7208 | X74: 67216 | Y74: 12 | Z74: 0 | AA74: 1336 | AB74: 159814 | AC74: 21% | AD74: RW Mercer - 0 | AM74: 0 | AN74: 56298 | AV74: =IF(A74="Awarded",IFERROR((N74-J74)/J74,"-"),"-") -> -
A75: Closed | B75: CCI Central MI | C75: Industrial/Power | D75: 8 | F75: 25-0914 | G75: Pfizer B41 SCO Dock Upgrade | H75: 8/14/2025 | J75: 124700 | K75: Kalamazoo, MI | L75: CON | M75: Dave Deller | R75: 26 | S75: 1285 | T75: 574 | V75: 336 | W75: 910 | X75: 12000 | Y75: 3 | Z75: 25819 | AA75: 304 | AB75: 27761 | AC75: 22% | AD75: The Austin Company - 0 | AM75: 0 | AN75: 18778 | AV75: =IF(A75="Awarded",IFERROR((N75-J75)/J75,"-"),"-") -> -
A76: Closed | B76: CCI Southeast MI | C76: Industrial/Power | D76: 8 | F76: 25-0707 | G76: MacAllister CAT - Metro South - Building & Site Concrete - Hagerman Inc. | H76: 8/15/2025 | J76: 826122 | K76: Brownstown Charter Township , MI | L76: CON | M76: Farzan Rafieyan-Esfahani | Q76: Bid was submitted to Hagerman through building connected. Shiel Sexton bid amount is $ 867,000 | R76: 1252 | S76: 37201 | T76: 3061 | V76: 1060 | W76: 4121 | X76: 74570 | Y76: 10 | Z76: 78658 | AA76: 920 | AB76: 117851 | AC76: 14% | AD76: Hagerman Inc. - 0 Shiel Sexton - 0 | AM76: 0 | AN76: 82647 | AV76: =IF(A76="Awarded",IFERROR((N76-J76)/J76,"-"),"-") -> -
A77: Closed | B77: CCI Central MI | C77: Health Care | D77: 8 | F77: 25-0728 | G77: Grand Ledge Medical Office Building | H77: 8/19/2025 | J77: 997000 | K77: Grand Ledge, MI | L77: CON | M77: Greg Klem | R77: 1336 | S77: 41044 | T77: 3726 | V77: 1225 | W77: 4951 | X77: 73669 | Y77: 11 | Z77: 89692 | AA77: 859 | AB77: 151674 | AC77: 15% | AD77: The Christman Company - 0 | AM77: 0 | AN77: 73966 | AV77: =IF(A77="Awarded",IFERROR((N77-J77)/J77,"-"),"-") -> -
A78: Awarded | B78: CCI Central MI | C78: Industrial/Power | D78: 8 | E78: 251137 | F78: 25-0915 | G78: Consumers Energy Overisel Air Receiver | H78: 8/28/2025 | I78: 10/13/2025 | J78: 95000 | K78: Hamilton, MI | L78: CON | M78: Dave Deller | N78: 95000 | O78: 9000 | P78: 488 | R78: 64 | S78: 328 | T78: 236 | V78: 252 | W78: 488 | X78: 9000 | Y78: 2 | Z78: 18690 | AA78: 168 | AB78: 31810 | AC78: 33% | AD78: Henkels & McCoy - 0 | AE78: 641.5 | AF78: 122756 | AG78: 5000 | AH78: 127756 | AI78: 3.9% | AJ78: Open | AK78: 45931 | AM78: 0 | AN78: 10540 | AV78: =IF(A78="Awarded",IFERROR((N78-J78)/J78,"-"),"-") -> 0
A79: Closed | B79: CCI Central MI | C79: Industrial/Power | D79: 8 | F79: 25-0917 | G79: Air Liquide Gernaat Interconnect | H79: 8/29/2025 | J79: 53750 | K79: Falmouth, MI | L79: CON | M79: Dave Deller | R79: 14 | S79: 16 | T79: 172 | V79: 138 | W79: 310 | X79: 5000 | Y79: 1 | Z79: 10308 | AA79: 112 | AB79: 17649 | AC79: 33% | AD79: Henkels & McCoy - 0 | AM79: 0 | AN79: 1900 | AV79: =IF(A79="Awarded",IFERROR((N79-J79)/J79,"-"),"-") -> -
A80: Closed | B80: CCI Southeast MI | C80: Other | D80: 9 | F80: 25-0916 | G80: Romulus Trade Center - Building 4 | H80: 9/2/2025 | J80: 3125795 | K80: Romulus, MI | L80: CON | M80: Sam Peterson | R80: 8224 | S80: 310793 | T80: 9371 | V80: 1832 | W80: 11203 | X80: 205327 | Y80: 14 | Z80: 165987 | AA80: 1544 | AB80: 261807 | AC80: 8% | AD80: Br - 0 | AM80: 0 | AN80: 104555 | AV80: =IF(A80="Awarded",IFERROR((N80-J80)/J80,"-"),"-") -> -
A81: Awarded | B81: CCI Central MI | C81: Other | D81: 9 | E81: 251162 | F81: 25-0830 | G81: Brent Run Bullet Tank | H81: 9/19/2025 | I81: 10/24/2025 | J81: 113493 | K81: Montrose, MI | L81: CON | M81: Farzan Rafieyan-Esfahani | N81: 113493 | O81: 14640 | P81: 732 | R81: 74 | S81: 1335 | T81: 436 | V81: 296 | W81: 732 | X81: 14640 | Y81: 3 | Z81: 22778 | AA81: 0 | AB81: 27583 | AC81: 24% | AD81: D & R Earthmoving LLC - 0 | AE81: 773 | AF81: 105000 | AG81: 13500 | AH81: 118500 | AI81: 11.4% | AJ81: Open | AK81: 45931 | AM81: 0 | AN81: 6549 | AV81: =IF(A81="Awarded",IFERROR((N81-J81)/J81,"-"),"-") -> 0
A82: Closed | B82: CCI Central MI | C82: Other | D82: 9 | F82: 25-0855 | G82: State Disposal Leachate Tank Installation | H82: 9/23/2025 | J82: 97300 | K82: Grand Rapids, MI | L82: CON | M82: Ron Cody | R82: 80 | S82: 540 | T82: 303 | V82: 240 | W82: 543 | X82: 13095 | Y82: 3 | Z82: 18065 | AA82: 204 | AB82: 23530 | AC82: 24% | AD82: D&R Earthmoving, LLC - 0 | AM82: 0 | AN82: 800 | AV82: =IF(A82="Awarded",IFERROR((N82-J82)/J82,"-"),"-") -> -
A83: Closed | B83: CCI Central MI | C83: Government | D83: 9 | F83: 25-0849 | G83: Mason DPW - Building Foundations | H83: 9/23/2025 | J83: 997000 | K83: Mason, MI | L83: CON | M83: Greg Klem | R83: 851 | S83: 45717 | T83: 4808 | V83: 1548 | W83: 6356 | X83: 63574 | Y83: 10 | Z83: 112908 | AA83: 1040 | AB83: 131474 | AC83: 13% | AD83: Clark Construction Company - 0 Quadrate - 0 | AM83: 0 | AN83: 64599 | AV83: =IF(A83="Awarded",IFERROR((N83-J83)/J83,"-"),"-") -> -
A84: Closed | B84: CCI Central MI | C84: Government | D84: 9 | F84: 25-0850 | G84: Mason DPW - Flatwork | H84: 9/23/2025 | J84: 727000 | K84: Mason, MI | L84: CON | M84: Greg Klem | R84: 1334 | S84: 46117 | T84: 2912 | V84: 848 | W84: 3760 | X84: 69337 | Y84: 6 | Z84: 61787 | AA84: 624 | AB84: 75232 | AC84: 10% | AD84: Clark Construction Company - 0 Quadrate - 0 | AM84: 0 | AN84: 74525 | AV84: =IF(A84="Awarded",IFERROR((N84-J84)/J84,"-"),"-") -> -
A85: Closed | B85: CCI Central MI | C85: Government | D85: 9 | F85: 25-0851 | G85: Mason DPW - Site Concrete | H85: 9/23/2025 | J85: 567000 | K85: Mason, MI | L85: CON | M85: Greg Klem | R85: 631 | S85: 20561 | T85: 1028 | V85: 508 | W85: 1536 | X85: 46499 | Y85: 6 | Z85: 38017 | AA85: 432 | AB85: 41453 | AC85: 7% | AD85: Clark Construction Company - 0 Quadrate - 0 | AM85: 0 | AN85: 7801 | AV85: =IF(A85="Awarded",IFERROR((N85-J85)/J85,"-"),"-") -> -
A86: Closed | B86: Out of Region | C86: Government | D86: 10 | F86: 25-0902 | G86: DTE - Clymers CO2 Capture Facility | H86: 10/7/2025 | J86: 1209792 | K86: Logansport , IN | L86: CON | M86: Farzan Rafieyan-Esfahani | Q86: Bid was submitted via email to Henkels & McCoy, and it included second proposal with limited scope which bid amount was $ 975,359.00 (Amount submitted to H & M $ 977,000.00) for 7 weeks duration. | R86: 1122 | S86: 5880 | T86: 2560 | V86: 1540 | W86: 4100 | X86: 103534 | Y86: 9 | Z86: 145193 | AA86: 856 | AB86: 283661 | AC86: 23% | AD86: Henkels & McCoy - 0 | AM86: 0 | AN86: 25188 | AV86: =IF(A86="Awarded",IFERROR((N86-J86)/J86,"-"),"-") -> -
A87: Closed | B87: CCI Central MI | C87: Sports / Event Venues | D87: 10 | F87: 25-0920 | G87: KCC Outbuildings | H87: 10/10/2025 | J87: 299000 | K87: kalamazoo, MI | L87: CON | M87: Ethan Conlan | R87: 105 | S87: 867 | T87: 2382 | V87: 870 | W87: 3252 | X87: 37121 | Y87: 7 | Z87: 0 | AA87: 448 | AB87: 80709 | AC87: 27% | AD87: CSM Group - 0 | AM87: 0 | AN87: 16010 | AV87: =IF(A87="Awarded",IFERROR((N87-J87)/J87,"-"),"-") -> -
A88: Closed | B88: CCI Southeast MI | C88: Other | D88: 10 | F88: 25-0924 | G88: Ottawa County Farms - Leachate Loadout Modifications | H88: 10/13/2025 | J88: 23000 | K88: Coopersville, MI | L88: CON | M88: Ethan Conlan | R88: 7 | S88: 158 | T88: 150 | V88: 58 | W88: 208 | X88: 5110 | Y88: 1 | Z88: 5022 | AA88: 40 | AB88: 8222 | AC88: 36% | AD88: DNR - 0 | AM88: 0 | AN88: 1030 | AV88: =IF(A88="Awarded",IFERROR((N88-J88)/J88,"-"),"-") -> -
A89: Closed | B89: CCI Central MI | C89: Industrial/Power | D89: 10 | F89: 25-0927 | G89: Nicor Gas Bloomington Compressor Station | H89: 10/14/2025 | J89: 847000 | K89: Gridley, IL | L89: CON | M89: Greg Klem | R89: 583 | S89: 11686 | T89: 2816 | V89: 1576 | W89: 4392 | X89: 112262 | Y89: 8 | Z89: 127261 | AA89: 6752 | AB89: 231981 | AC89: 27% | AD89: Henkels & McCoy - 0 | AM89: 0 | AN89: 29100 | AV89: =IF(A89="Awarded",IFERROR((N89-J89)/J89,"-"),"-") -> -
A90: Closed | B90: CCI Central MI | C90: Office | D90: 10 | F90: 25-0943 | G90: AWS-CMH165-Security Building | H90: 10/16/2025 | J90: 275000 | K90: Wilmington, OH | L90: CON | M90: Ethan Conlan | R90: 126 | S90: 1043 | T90: 1298 | V90: 540 | W90: 1838 | X90: 31974 | Y90: 4 | Z90: 0 | AA90: 296 | AB90: 78578 | AC90: 29% | AD90: Skanska - 0 | AM90: 0 | AN90: 15990 | AV90: =IF(A90="Awarded",IFERROR((N90-J90)/J90,"-"),"-") -> -
A91: Closed | B91: CCI Central MI | C91: Church | D91: 11 | F91: 25-1010 | G91: St. Thomas Aquinas | H91: 11/4/2025 | J91: 47000 | K91: East Lansing, MI | L91: CON | M91: Greg Klem | Q91: Add Alternate to Excavate and Backfill - $10,000 | R91: 20 | S91: 870 | T91: 264 | V91: 124 | W91: 388 | X91: 9587 | Y91: 2 | Z91: 9595 | AA91: 112 | AB91: 10821 | AC91: 23% | AD91: - 0 | AM91: 0 | AN91: 4337 | AV91: =IF(A91="Awarded",IFERROR((N91-J91)/J91,"-"),"-") -> -
A92: Closed | B92: CCI Southeast MI | C92: Residential/ Housing | D92: 11 | F92: 25-1020 | G92: UM Student & Faculty Housing - 003A Building Concrete Flatwork | H92: 11/7/2025 | J92: 2037500 | K92: Detroit, MI | L92: CON | M92: Greg Klem | P92: 0 | R92: 3393 | S92: 204612 | T92: 6853 | V92: 3432 | W92: 10285 | X92: 164768 | Y92: 24 | Z92: 254289 | AA92: 2496 | AB92: 301497 | AC92: 15% | AD92: Clark Construction Company - 0 | AM92: 0 | AN92: 149868 | AV92: =IF(A92="Awarded",IFERROR((N92-J92)/J92,"-"),"-") -> -
A93: Closed | B93: CCI Southeast MI | C93: Residential/ Housing | D93: 11 | F93: 25-1021 | G93: UM Student & Faculty Housing - 003B Foundations & Structural Concrete | H93: 11/7/2025 | J93: 3516500 | K93: Detroit, MI | L93: CON | M93: Greg Klem | R93: 3685 | S93: 38857 | T93: 6596 | V93: 2394 | W93: 8990 | X93: 222034 | Y93: 12 | Z93: 224726 | AA93: 1848 | AB93: 429412 | AC93: 12% | AD93: Clark Construction Company - 0 | AM93: 0 | AN93: 198837 | AV93: =IF(A93="Awarded",IFERROR((N93-J93)/J93,"-"),"-") -> -
A94: Closed | B94: CCI Central MI | C94: Industrial/Power | D94: 11 | F94: 25-1028 | G94: LBWL Steam Conversion Station and Chilled Water Pipe Relocation - Concrete | H94: 11/7/2025 | J94: 277000 | K94: Lansing, MI | L94: CON | M94: Ethan Conlan | P94: 0 | R94: 108 | S94: 1787 | T94: 1320 | V94: 388 | W94: 1708 | X94: 30513 | Y94: 4 | Z94: 29914 | AA94: 240 | AB94: 43314 | AC94: 16% | AD94: Northern Boiler - 0 | AM94: 0 | AN94: 37537 | AV94: =IF(A94="Awarded",IFERROR((N94-J94)/J94,"-"),"-") -> -
A95: Closed | B95: CCI Southeast MI | C95: Residential/ Housing | D95: 11 | F95: 25-1041 | G95: 625 Church Street Ann Arbor | H95: 11/11/2025 | J95: 18250000 | K95: Ann Arbor, MI | L95: CON | M95: Dave Deller | R95: 12107 | S95: 285000 | T95: 60015 | V95: 12616 | W95: 72631 | X95: 1551979 | Y95: 52 | Z95: 1387633 | AA95: 10312 | AB95: 2718816 | AC95: 15% | AD95: Power Construction - 0 | AM95: 0 | AN95: 515982 | AV95: =IF(A95="Awarded",IFERROR((N95-J95)/J95,"-"),"-") -> -
A96: Closed | B96: CCI West Michigan | C96: Government | D96: 11 | F96: 25-1056 | G96: Coolwater Facility WC 10 Structural Concrete | H96: 11/18/2025 | J96: 793000 | K96: Mattawan, MI | L96: CON | M96: Greg Klem | R96: 620 | S96: 12667 | T96: 3046 | V96: 2022 | W96: 5068 | X96: 94653 | Y96: 19 | Z96: 149594 | AA96: 1376 | AB96: 192074 | AC96: 24% | AD96: The Christman Company - 0 | AM96: 0 | AN96: 64701 | AV96: =IF(A96="Awarded",IFERROR((N96-J96)/J96,"-"),"-") -> -
A97: Open | B97: CCI Southeast MI | C97: Government | D97: 12 | F97: 25-1130 | G97: Bluewater Bridge Concrete | H97: 12/12/2025 | J97: 9197000 | K97: Port Huron, MI | L97: CON | M97: Greg Klem | R97: 5290 | S97: 78577 | T97: 24451 | V97: 14362 | W97: 38813 | X97: 822114 | Y97: 72 | Z97: 1220598 | AA97: 10368 | AB97: 2063672 | AC97: 22% | AD97: The Christman Company - 0 | AM97: 0 | AN97: 1115762 | AV97: =IF(A97="Awarded",IFERROR((N97-J97)/J97,"-"),"-") -> -
A98: Closed | B98: CCI Southeast MI | C98: Health Care | D98: 12 | F98: 25-1131 | G98: Quest Diagnostics Project Pepper Concrete | H98: 12/12/2025 | J98: 267000 | K98: Southfield, MI | L98: CON | M98: Ethan Conlan | R98: 137 | S98: 974 | T98: 1054 | V98: 391 | W98: 1445 | X98: 32320 | Y98: 6 | Z98: 0 | AA98: 360 | AB98: 38932 | AC98: 15% | AD98: Turner Construction Company - 0 | AM98: 0 | AN98: 34733 | AV98: =IF(A98="Awarded",IFERROR((N98-J98)/J98,"-"),"-") -> -
A99: Closed | B99: CCI Central MI | C99: Industrial/Power | D99: 12 | F99: 26-0029 | G99: TC Energy Lake George Concrete | H99: 12/12/2025 | J99: 1167000 | K99: Lake Georger, MI | L99: CON | M99: Dave Deller | R99: 1200 | S99: 19200 | T99: 2630 | V99: 1408 | W99: 4038 | X99: 110000 | Y99: 8 | Z99: 115759 | AA99: 832 | AB99: 217500 | AC99: 19% | AD99: Michels Pipeline, Inc. - 0 | AM99: 0 | AN99: 39757 | AV99: =IF(A99="Awarded",IFERROR((N99-J99)/J99,"-"),"-") -> -
A100: Open | B100: Out of Region | C100: Industrial/Power | D100: 12 | F100: 25-1134 | G100: Tallgrass SIRE Capture Facility - Concrete | H100: 12/17/2025 | J100: 1724000 | K100: Council Bluffs, IA | L100: CON | M100: Ethan Conlan | R100: 1532 | S100: 16314 | T100: 5681 | V100: 2664 | W100: 8345 | X100: 173992 | Y100: 16 | Z100: 256672 | AA100: 1920 | AB100: 339793 | AC100: 20% | AD100: Henkels & McCoy - 0 | AM100: 0 | AN100: 45302 | AV100: =IF(A100="Awarded",IFERROR((N100-J100)/J100,"-"),"-") -> -
...

Sheet Data Dictionary
A1: Column Name | B1: Type | C1: Values / Format | D1: Purpose / Why It Matters
A2: Status ✅ | B2: Dropdown (existing) | C2: Awarded / Closed / Open | D2: Core outcome — determines if bid is included in hit rate calc
A3: Bid Amount ✅ | B3: Currency (existing) | C3: $#,##0 | D3: Our submitted price
A4: Contract Amount ✅ | B4: Currency (existing) | C4: $#,##0 | D4: Final contract value on awarded work
A5: Market Sector ✅ | B5: Text (existing) | C5: Healthcare, Industrial/Power, etc. | D5: Allows segmentation of win rates by project type
A6: Estimator ✅ | B6: Text (existing) | C6: Name | D6: Attribution for hit rate analysis per estimator
A7: Region ✅ | B7: Text (existing) | C7: CCI Southeast MI, etc. | D7: Regional performance comparison
A9: Delivery Method 🆕 | B9: Dropdown (NEW) | C9: Hard Bid / Negotiated / CM at Risk / Design-Build / Other | D9: CRITICAL — your negotiated hit rate is almost certainly far higher than hard bid. Mixing them distorts your ratio. Segment immediately.
A10: # of Bidders 🆕 | B10: Whole number (NEW) | C10: 1 – 20 | D10: Normalizes hit rate. 1 of 8 bidders at 12% is average; 1 of 2 at 50% is underperforming if you had the relationship.
A11: Opportunity Source 🆕 | B11: Dropdown (NEW) | C11: Existing Customer / Referral / Repeat Work / Cold RFP / Owner Direct / Other | D11: Identifies which lead sources convert best. Helps decide where estimating hours are worth spending.
A12: Go/No-Go Score 🆕 | B12: Dropdown (NEW) | C12: 1=Low / 2=Medium / 3=High | D12: Captures confidence AT TIME OF BID. Compare hit rate of Score-3 bids vs Score-1 — if they're similar, your scoring model needs work.
A13: Loss Reason 🆕 | B13: Dropdown (NEW) | C13: Price Too High / No Relationship / Scope Mismatch / Competitor Relationship / No-Bid After Review / Budget Cut / Unknown | D13: The single most valuable new column. Without this, 'Closed' is a black hole. Lets you distinguish pricing misses from unwinnable bids.
... A16: Bid Delta % 🆕 | B16: Formula (AUTO) | C16: Auto-calculated: (Contract − Bid) / Bid | D16: Shows how accurate your estimating is on wins. Consistently negative = leaving money on the table. Consistently high = you got lucky or scope changed.
